dixa/__init__.py
dixa/api/__init__.py
dixa/api/v1/__init__.py
dixa/api/v1/agents.py
dixa/api/v1/analytics.py
dixa/api/v1/contact_endpoints.py
dixa/api/v1/conversations.py
dixa/api/v1/custom_attributes.py
dixa/api/v1/end_users.py
dixa/api/v1/queues.py
dixa/api/v1/tags.py
dixa/api/v1/teams.py
dixa/api/v1/webhooks.py
dixa_api-1.0.0.dist-info/LICENSE
dixa_api-1.0.0.dist-info/METADATA
dixa_api-1.0.0.dist-info/WHEEL
dixa_api-1.0.0.dist-info/top_level.txt
dixa_api-1.0.0.dist-info/RECORD
