Metadata-Version: 2.1
Name: dixa-api
Version: 1.0.0
Summary: Python API Client for Dixa
Author-email: ChemicalLuck <j.tebbett@outlook.com>
Project-URL: Homepage, http://github.com/ChemicalLuck/dixa-api
Classifier: Development Status :: 3 - Alpha
Classifier: Intended Audience :: Information Technology
Classifier: License :: OSI Approved :: MIT License
Classifier: Natural Language :: English
Classifier: Programming Language :: Python :: 3
Classifier: Topic :: Software Development :: Libraries :: Python Modules
Classifier: Topic :: Software Development :: Testing
Classifier: Topic :: Utilities
Requires-Python: >=3.11
License-File: LICENSE
Requires-Dist: requests
